// 
// Decompiled by Procyon v0.5.30
// 

package com.baidu.location.d;

class g extends Thread
{
    final /* synthetic */ String a;
    final /* synthetic */ boolean b;
    final /* synthetic */ e c;
    
    g(final e c, final String a, final boolean b) {
        this.c = c;
        this.a = a;
        this.b = b;
    }
    
    public void run() {
        // 
        // This method could not be decompiled.
        // 
        // Original Bytecode:
        // 
        //     0: aload_0        
        //     1: getfield        com/baidu/location/d/g.c:Lcom/baidu/location/d/e;
        //     4: astore_1       
        //     5: invokestatic    com/baidu/location/d/j.c:()Ljava/lang/String;
        //     8: astore_2       
        //     9: aload_1        
        //    10: aload_2        
        //    11: putfield        com/baidu/location/d/e.h:Ljava/lang/String;
        //    14: aload_0        
        //    15: getfield        com/baidu/location/d/g.c:Lcom/baidu/location/d/e;
        //    18: invokestatic    com/baidu/location/d/e.a:(Lcom/baidu/location/d/e;)V
        //    21: aload_0        
        //    22: getfield        com/baidu/location/d/g.c:Lcom/baidu/location/d/e;
        //    25: invokevirtual   com/baidu/location/d/e.a:()V
        //    28: aload_0        
        //    29: getfield        com/baidu/location/d/g.c:Lcom/baidu/location/d/e;
        //    32: astore_1       
        //    33: aload_1        
        //    34: getfield        com/baidu/location/d/e.i:I
        //    37: istore_3       
        //    38: aconst_null    
        //    39: astore_2       
        //    40: iconst_0       
        //    41: istore          4
        //    43: aconst_null    
        //    44: astore          5
        //    46: iconst_1       
        //    47: istore          6
        //    49: iload_3        
        //    50: ifle            1392
        //    53: new             Ljava/net/URL;
        //    56: astore          7
        //    58: aload_0        
        //    59: getfield        com/baidu/location/d/g.c:Lcom/baidu/location/d/e;
        //    62: astore          8
        //    64: aload           8
        //    66: getfield        com/baidu/location/d/e.h:Ljava/lang/String;
        //    69: astore          8
        //    71: aload           7
        //    73: aload           8
        //    75: invokespecial   java/net/URL.<init>:(Ljava/lang/String;)V
        //    78: new             Ljava/lang/StringBuffer;
        //    81: astore          8
        //    83: aload           8
        //    85: invokespecial   java/lang/StringBuffer.<init>:()V
        //    88: aload_0        
        //    89: getfield        com/baidu/location/d/g.c:Lcom/baidu/location/d/e;
        //    92: astore          9
        //    94: aload           9
        //    96: getfield        com/baidu/location/d/e.k:Ljava/util/Map;
        //    99: astore          9
        //   101: aload           9
        //   103: invokeinterface java/util/Map.entrySet:()Ljava/util/Set;
        //   108: astore          9
        //   110: aload           9
        //   112: invokeinterface java/util/Set.iterator:()Ljava/util/Iterator;
        //   117: astore          9
        //   119: aload           9
        //   121: invokeinterface java/util/Iterator.hasNext:()Z
        //   126: istore          10
        //   128: iload           10
        //   130: ifeq            217
        //   133: aload           9
        //   135: invokeinterface java/util/Iterator.next:()Ljava/lang/Object;
        //   140: astore          11
        //   142: aload           11
        //   144: checkcast       Ljava/util/Map$Entry;
        //   147: astore          11
        //   149: aload           11
        //   151: invokeinterface java/util/Map$Entry.getKey:()Ljava/lang/Object;
        //   156: astore          12
        //   158: aload           12
        //   160: checkcast       Ljava/lang/String;
        //   163: astore          12
        //   165: aload           8
        //   167: aload           12
        //   169: invokevirtual   java/lang/StringBuffer.append:(Ljava/lang/String;)Ljava/lang/StringBuffer;
        //   172: pop            
        //   173: ldc             "="
        //   175: astore          12
        //   177: aload           8
        //   179: aload           12
        //   181: invokevirtual   java/lang/StringBuffer.append:(Ljava/lang/String;)Ljava/lang/StringBuffer;
        //   184: pop            
        //   185: aload           11
        //   187: invokeinterface java/util/Map$Entry.getValue:()Ljava/lang/Object;
        //   192: astore          11
        //   194: aload           8
        //   196: aload           11
        //   198: invokevirtual   java/lang/StringBuffer.append:(Ljava/lang/Object;)Ljava/lang/StringBuffer;
        //   201: pop            
        //   202: ldc             "&"
        //   204: astore          11
        //   206: aload           8
        //   208: aload           11
        //   210: invokevirtual   java/lang/StringBuffer.append:(Ljava/lang/String;)Ljava/lang/StringBuffer;
        //   213: pop            
        //   214: goto            119
        //   217: aload           8
        //   219: invokevirtual   java/lang/StringBuffer.length:()I
        //   222: istore          13
        //   224: iload           13
        //   226: ifle            247
        //   229: aload           8
        //   231: invokevirtual   java/lang/StringBuffer.length:()I
        //   234: iload           6
        //   236: isub           
        //   237: istore          13
        //   239: aload           8
        //   241: iload           13
        //   243: invokevirtual   java/lang/StringBuffer.deleteCharAt:(I)Ljava/lang/StringBuffer;
        //   246: pop            
        //   247: aload           7
        //   249: invokevirtual   java/net/URL.openConnection:()Ljava/net/URLConnection;
        //   252: astore          7
        //   254: aload           7
        //   256: checkcast       Ljava/net/HttpURLConnection;
        //   259: astore          7
        //   261: ldc             "POST"
        //   263: astore          5
        //   265: aload           7
        //   267: aload           5
        //   269: invokevirtual   java/net/HttpURLConnection.setRequestMethod:(Ljava/lang/String;)V
        //   272: aload           7
        //   274: iload           6
        //   276: invokevirtual   java/net/HttpURLConnection.setDoInput:(Z)V
        //   279: aload           7
        //   281: iload           6
        //   283: invokevirtual   java/net/HttpURLConnection.setDoOutput:(Z)V
        //   286: aload           7
        //   288: iconst_0       
        //   289: invokevirtual   java/net/HttpURLConnection.setUseCaches:(Z)V
        //   292: getstatic       com/baidu/location/d/a.b:I
        //   295: istore          4
        //   297: aload           7
        //   299: iload           4
        //   301: invokevirtual   java/net/HttpURLConnection.setConnectTimeout:(I)V
        //   304: getstatic       com/baidu/location/d/a.b:I
        //   307: istore          4
        //   309: aload           7
        //   311: iload           4
        //   313: invokevirtual   java/net/HttpURLConnection.setReadTimeout:(I)V
        //   316: ldc             "Content-Type"
        //   318: astore          5
        //   320: ldc             "application/x-www-form-urlencoded; charset=utf-8"
        //   322: astore          9
        //   324: aload           7
        //   326: aload           5
        //   328: aload           9
        //   330: invokevirtual   java/net/HttpURLConnection.setRequestProperty:(Ljava/lang/String;Ljava/lang/String;)V
        //   333: ldc             "Accept-Charset"
        //   335: astore          5
        //   337: ldc             "UTF-8"
        //   339: astore          9
        //   341: aload           7
        //   343: aload           5
        //   345: aload           9
        //   347: invokevirtual   java/net/HttpURLConnection.setRequestProperty:(Ljava/lang/String;Ljava/lang/String;)V
        //   350: ldc             "Accept-Encoding"
        //   352: astore          5
        //   354: ldc             "gzip"
        //   356: astore          9
        //   358: aload           7
        //   360: aload           5
        //   362: aload           9
        //   364: invokevirtual   java/net/HttpURLConnection.setRequestProperty:(Ljava/lang/String;Ljava/lang/String;)V
        //   367: aload_0        
        //   368: getfield        com/baidu/location/d/g.a:Ljava/lang/String;
        //   371: astore          5
        //   373: aload           5
        //   375: invokestatic    android/text/TextUtils.isEmpty:(Ljava/lang/CharSequence;)Z
        //   378: istore          4
        //   380: iload           4
        //   382: ifne            404
        //   385: ldc             "Host"
        //   387: astore          5
        //   389: aload_0        
        //   390: getfield        com/baidu/location/d/g.a:Ljava/lang/String;
        //   393: astore          9
        //   395: aload           7
        //   397: aload           5
        //   399: aload           9
        //   401: invokevirtual   java/net/HttpURLConnection.setRequestProperty:(Ljava/lang/String;Ljava/lang/String;)V
        //   404: aload           7
        //   406: invokevirtual   java/net/HttpURLConnection.getOutputStream:()Ljava/io/OutputStream;
        //   409: astore          5
        //   411: aload           8
        //   413: invokevirtual   java/lang/StringBuffer.toString:()Ljava/lang/String;
        //   416: astore          8
        //   418: aload           8
        //   420: invokevirtual   java/lang/String.getBytes:()[B
        //   423: astore          8
        //   425: aload           5
        //   427: aload           8
        //   429: invokevirtual   java/io/OutputStream.write:([B)V
        //   432: aload           5
        //   434: invokevirtual   java/io/OutputStream.flush:()V
        //   437: aload           7
        //   439: invokevirtual   java/net/HttpURLConnection.getResponseCode:()I
        //   442: istore          14
        //   444: sipush          200
        //   447: istore          13
        //   449: iload           14
        //   451: iload           13
        //   453: if_icmpne       708
        //   456: aload           7
        //   458: invokevirtual   java/net/HttpURLConnection.getInputStream:()Ljava/io/InputStream;
        //   461: astore          8
        //   463: aload           7
        //   465: invokevirtual   java/net/HttpURLConnection.getContentEncoding:()Ljava/lang/String;
        //   468: astore          9
        //   470: aload           9
        //   472: ifnull          521
        //   475: ldc             "gzip"
        //   477: astore          11
        //   479: aload           9
        //   481: aload           11
        //   483: invokevirtual   java/lang/String.contains:(Ljava/lang/CharSequence;)Z
        //   486: istore          13
        //   488: iload           13
        //   490: ifeq            521
        //   493: new             Ljava/util/zip/GZIPInputStream;
        //   496: astore          9
        //   498: new             Ljava/io/BufferedInputStream;
        //   501: astore          11
        //   503: aload           11
        //   505: aload           8
        //   507: invokespecial   java/io/BufferedInputStream.<init>:(Ljava/io/InputStream;)V
        //   510: aload           9
        //   512: aload           11
        //   514: invokespecial   java/util/zip/GZIPInputStream.<init>:(Ljava/io/InputStream;)V
        //   517: aload           9
        //   519: astore          8
        //   521: new             Ljava/io/ByteArrayOutputStream;
        //   524: astore          9
        //   526: aload           9
        //   528: invokespecial   java/io/ByteArrayOutputStream.<init>:()V
        //   531: sipush          1024
        //   534: istore          10
        //   536: iload           10
        //   538: newarray        B
        //   540: astore          11
        //   542: aload           8
        //   544: aload           11
        //   546: invokevirtual   java/io/InputStream.read:([B)I
        //   549: istore          15
        //   551: iconst_m1      
        //   552: istore          16
        //   554: iload           15
        //   556: iload           16
        //   558: if_icmpeq       574
        //   561: aload           9
        //   563: aload           11
        //   565: iconst_0       
        //   566: iload           15
        //   568: invokevirtual   java/io/ByteArrayOutputStream.write:([BII)V
        //   571: goto            542
        //   574: aload_0        
        //   575: getfield        com/baidu/location/d/g.c:Lcom/baidu/location/d/e;
        //   578: astore          11
        //   580: new             Ljava/lang/String;
        //   583: astore          12
        //   585: aload           9
        //   587: invokevirtual   java/io/ByteArrayOutputStream.toByteArray:()[B
        //   590: astore          17
        //   592: ldc             "utf-8"
        //   594: astore          18
        //   596: aload           12
        //   598: aload           17
        //   600: aload           18
        //   602: invokespecial   java/lang/String.<init>:([BLjava/lang/String;)V
        //   605: aload           11
        //   607: aload           12
        //   609: putfield        com/baidu/location/d/e.j:Ljava/lang/String;
        //   612: aload_0        
        //   613: getfield        com/baidu/location/d/g.b:Z
        //   616: istore          10
        //   618: iload           10
        //   620: ifeq            643
        //   623: aload_0        
        //   624: getfield        com/baidu/location/d/g.c:Lcom/baidu/location/d/e;
        //   627: astore          11
        //   629: aload           9
        //   631: invokevirtual   java/io/ByteArrayOutputStream.toByteArray:()[B
        //   634: astore          12
        //   636: aload           11
        //   638: aload           12
        //   640: putfield        com/baidu/location/d/e.m:[B
        //   643: aload_0        
        //   644: getfield        com/baidu/location/d/g.c:Lcom/baidu/location/d/e;
        //   647: astore          11
        //   649: aload           11
        //   651: iload           6
        //   653: invokevirtual   com/baidu/location/d/e.a:(Z)V
        //   656: iconst_1       
        //   657: istore          10
        //   659: goto            726
        //   662: astore_1       
        //   663: goto            852
        //   666: astore          11
        //   668: goto            872
        //   671: astore          11
        //   673: goto            901
        //   676: astore_1       
        //   677: iconst_0       
        //   678: istore          13
        //   680: aconst_null    
        //   681: astore          9
        //   683: goto            852
        //   686: astore          9
        //   688: iconst_0       
        //   689: istore          13
        //   691: aconst_null    
        //   692: astore          9
        //   694: goto            872
        //   697: astore          9
        //   699: iconst_0       
        //   700: istore          13
        //   702: aconst_null    
        //   703: astore          9
        //   705: goto            901
        //   708: iconst_0       
        //   709: istore          14
        //   711: aconst_null    
        //   712: astore          8
        //   714: iconst_0       
        //   715: istore          13
        //   717: aconst_null    
        //   718: astore          9
        //   720: iconst_0       
        //   721: istore          10
        //   723: aconst_null    
        //   724: astore          11
        //   726: aload           7
        //   728: ifnull          736
        //   731: aload           7
        //   733: invokevirtual   java/net/HttpURLConnection.disconnect:()V
        //   736: aload           5
        //   738: ifnull          768
        //   741: aload           5
        //   743: invokevirtual   java/io/OutputStream.close:()V
        //   746: goto            768
        //   749: astore          5
        //   751: getstatic       com/baidu/location/d/a.a:Ljava/lang/String;
        //   754: astore          5
        //   756: ldc             "close os IOException!"
        //   758: astore          12
        //   760: aload           5
        //   762: aload           12
        //   764: invokestatic    android/util/Log.d:(Ljava/lang/String;Ljava/lang/String;)I
        //   767: pop            
        //   768: aload           8
        //   770: ifnull          800
        //   773: aload           8
        //   775: invokevirtual   java/io/InputStream.close:()V
        //   778: goto            800
        //   781: astore          5
        //   783: getstatic       com/baidu/location/d/a.a:Ljava/lang/String;
        //   786: astore          5
        //   788: ldc             "close is IOException!"
        //   790: astore          8
        //   792: aload           5
        //   794: aload           8
        //   796: invokestatic    android/util/Log.d:(Ljava/lang/String;Ljava/lang/String;)I
        //   799: pop            
        //   800: aload           9
        //   802: ifnull          832
        //   805: aload           9
        //   807: invokevirtual   java/io/ByteArrayOutputStream.close:()V
        //   810: goto            832
        //   813: astore          5
        //   815: getstatic       com/baidu/location/d/a.a:Ljava/lang/String;
        //   818: astore          5
        //   820: ldc             "close baos IOException!"
        //   822: astore          8
        //   824: aload           5
        //   826: aload           8
        //   828: invokestatic    android/util/Log.d:(Ljava/lang/String;Ljava/lang/String;)I
        //   831: pop            
        //   832: aload           7
        //   834: astore          5
        //   836: goto            1273
        //   839: astore_1       
        //   840: iconst_0       
        //   841: istore          14
        //   843: aconst_null    
        //   844: astore          8
        //   846: iconst_0       
        //   847: istore          13
        //   849: aconst_null    
        //   850: astore          9
        //   852: aload           5
        //   854: astore_2       
        //   855: goto            1295
        //   858: astore          8
        //   860: iconst_0       
        //   861: istore          14
        //   863: aconst_null    
        //   864: astore          8
        //   866: iconst_0       
        //   867: istore          13
        //   869: aconst_null    
        //   870: astore          9
        //   872: aload           7
        //   874: astore          19
        //   876: aload           5
        //   878: astore          7
        //   880: aload           19
        //   882: astore          5
        //   884: goto            1017
        //   887: astore          8
        //   889: iconst_0       
        //   890: istore          14
        //   892: aconst_null    
        //   893: astore          8
        //   895: iconst_0       
        //   896: istore          13
        //   898: aconst_null    
        //   899: astore          9
        //   901: aload           7
        //   903: astore          19
        //   905: aload           5
        //   907: astore          7
        //   909: aload           19
        //   911: astore          5
        //   913: goto            1143
        //   916: astore_1       
        //   917: iconst_0       
        //   918: istore          14
        //   920: aconst_null    
        //   921: astore          8
        //   923: iconst_0       
        //   924: istore          13
        //   926: aconst_null    
        //   927: astore          9
        //   929: goto            1295
        //   932: astore          5
        //   934: iconst_0       
        //   935: istore          14
        //   937: aconst_null    
        //   938: astore          8
        //   940: iconst_0       
        //   941: istore          13
        //   943: aconst_null    
        //   944: astore          9
        //   946: aload           7
        //   948: astore          5
        //   950: aconst_null    
        //   951: astore          7
        //   953: goto            1017
        //   956: astore          5
        //   958: iconst_0       
        //   959: istore          14
        //   961: aconst_null    
        //   962: astore          8
        //   964: iconst_0       
        //   965: istore          13
        //   967: aconst_null    
        //   968: astore          9
        //   970: aload           7
        //   972: astore          5
        //   974: aconst_null    
        //   975: astore          7
        //   977: goto            1143
        //   980: astore_1       
        //   981: iconst_0       
        //   982: istore          14
        //   984: aconst_null    
        //   985: astore          8
        //   987: iconst_0       
        //   988: istore          13
        //   990: aconst_null    
        //   991: astore          9
        //   993: aload           5
        //   995: astore          7
        //   997: goto            1295
        //  1000: astore          7
        //  1002: aconst_null    
        //  1003: astore          7
        //  1005: iconst_0       
        //  1006: istore          14
        //  1008: aconst_null    
        //  1009: astore          8
        //  1011: iconst_0       
        //  1012: istore          13
        //  1014: aconst_null    
        //  1015: astore          9
        //  1017: getstatic       com/baidu/location/d/a.a:Ljava/lang/String;
        //  1020: astore          11
        //  1022: ldc             "NetworkCommunicationError!"
        //  1024: astore          12
        //  1026: aload           11
        //  1028: aload           12
        //  1030: invokestatic    android/util/Log.d:(Ljava/lang/String;Ljava/lang/String;)I
        //  1033: pop            
        //  1034: aload           5
        //  1036: ifnull          1044
        //  1039: aload           5
        //  1041: invokevirtual   java/net/HttpURLConnection.disconnect:()V
        //  1044: aload           7
        //  1046: ifnull          1076
        //  1049: aload           7
        //  1051: invokevirtual   java/io/OutputStream.close:()V
        //  1054: goto            1076
        //  1057: astore          7
        //  1059: getstatic       com/baidu/location/d/a.a:Ljava/lang/String;
        //  1062: astore          7
        //  1064: ldc             "close os IOException!"
        //  1066: astore          11
        //  1068: aload           7
        //  1070: aload           11
        //  1072: invokestatic    android/util/Log.d:(Ljava/lang/String;Ljava/lang/String;)I
        //  1075: pop            
        //  1076: aload           8
        //  1078: ifnull          1108
        //  1081: aload           8
        //  1083: invokevirtual   java/io/InputStream.close:()V
        //  1086: goto            1108
        //  1089: astore          7
        //  1091: getstatic       com/baidu/location/d/a.a:Ljava/lang/String;
        //  1094: astore          7
        //  1096: ldc             "close is IOException!"
        //  1098: astore          8
        //  1100: aload           7
        //  1102: aload           8
        //  1104: invokestatic    android/util/Log.d:(Ljava/lang/String;Ljava/lang/String;)I
        //  1107: pop            
        //  1108: aload           9
        //  1110: ifnull          1267
        //  1113: aload           9
        //  1115: invokevirtual   java/io/ByteArrayOutputStream.close:()V
        //  1118: goto            1267
        //  1121: astore          7
        //  1123: goto            1250
        //  1126: astore          7
        //  1128: aconst_null    
        //  1129: astore          7
        //  1131: iconst_0       
        //  1132: istore          14
        //  1134: aconst_null    
        //  1135: astore          8
        //  1137: iconst_0       
        //  1138: istore          13
        //  1140: aconst_null    
        //  1141: astore          9
        //  1143: getstatic       com/baidu/location/d/a.a:Ljava/lang/String;
        //  1146: astore          11
        //  1148: ldc_w           "NetworkCommunicationException!"
        //  1151: astore          12
        //  1153: aload           11
        //  1155: aload           12
        //  1157: invokestatic    android/util/Log.d:(Ljava/lang/String;Ljava/lang/String;)I
        //  1160: pop            
        //  1161: aload           5
        //  1163: ifnull          1171
        //  1166: aload           5
        //  1168: invokevirtual   java/net/HttpURLConnection.disconnect:()V
        //  1171: aload           7
        //  1173: ifnull          1203
        //  1176: aload           7
        //  1178: invokevirtual   java/io/OutputStream.close:()V
        //  1181: goto            1203
        //  1184: astore          7
        //  1186: getstatic       com/baidu/location/d/a.a:Ljava/lang/String;
        //  1189: astore          7
        //  1191: ldc             "close os IOException!"
        //  1193: astore          11
        //  1195: aload           7
        //  1197: aload           11
        //  1199: invokestatic    android/util/Log.d:(Ljava/lang/String;Ljava/lang/String;)I
        //  1202: pop            
        //  1203: aload           8
        //  1205: ifnull          1235
        //  1208: aload           8
        //  1210: invokevirtual   java/io/InputStream.close:()V
        //  1213: goto            1235
        //  1216: astore          7
        //  1218: getstatic       com/baidu/location/d/a.a:Ljava/lang/String;
        //  1221: astore          7
        //  1223: ldc             "close is IOException!"
        //  1225: astore          8
        //  1227: aload           7
        //  1229: aload           8
        //  1231: invokestatic    android/util/Log.d:(Ljava/lang/String;Ljava/lang/String;)I
        //  1234: pop            
        //  1235: aload           9
        //  1237: ifnull          1267
        //  1240: aload           9
        //  1242: invokevirtual   java/io/ByteArrayOutputStream.close:()V
        //  1245: goto            1267
        //  1248: astore          7
        //  1250: getstatic       com/baidu/location/d/a.a:Ljava/lang/String;
        //  1253: astore          7
        //  1255: ldc             "close baos IOException!"
        //  1257: astore          8
        //  1259: aload           7
        //  1261: aload           8
        //  1263: invokestatic    android/util/Log.d:(Ljava/lang/String;Ljava/lang/String;)I
        //  1266: pop            
        //  1267: iconst_0       
        //  1268: istore          10
        //  1270: aconst_null    
        //  1271: astore          11
        //  1273: iload           10
        //  1275: ifeq            1281
        //  1278: goto            1392
        //  1281: iload_3        
        //  1282: iconst_m1      
        //  1283: iadd           
        //  1284: istore_3       
        //  1285: goto            46
        //  1288: astore_1       
        //  1289: aload           7
        //  1291: astore_2       
        //  1292: goto            993
        //  1295: aload           7
        //  1297: ifnull          1305
        //  1300: aload           7
        //  1302: invokevirtual   java/net/HttpURLConnection.disconnect:()V
        //  1305: aload_2        
        //  1306: ifnull          1332
        //  1309: aload_2        
        //  1310: invokevirtual   java/io/OutputStream.close:()V
        //  1313: goto            1332
        //  1316: astore_2       
        //  1317: getstatic       com/baidu/location/d/a.a:Ljava/lang/String;
        //  1320: astore_2       
        //  1321: ldc             "close os IOException!"
        //  1323: astore          5
        //  1325: aload_2        
        //  1326: aload           5
        //  1328: invokestatic    android/util/Log.d:(Ljava/lang/String;Ljava/lang/String;)I
        //  1331: pop            
        //  1332: aload           8
        //  1334: ifnull          1361
        //  1337: aload           8
        //  1339: invokevirtual   java/io/InputStream.close:()V
        //  1342: goto            1361
        //  1345: astore_2       
        //  1346: getstatic       com/baidu/location/d/a.a:Ljava/lang/String;
        //  1349: astore_2       
        //  1350: ldc             "close is IOException!"
        //  1352: astore          5
        //  1354: aload_2        
        //  1355: aload           5
        //  1357: invokestatic    android/util/Log.d:(Ljava/lang/String;Ljava/lang/String;)I
        //  1360: pop            
        //  1361: aload           9
        //  1363: ifnull          1390
        //  1366: aload           9
        //  1368: invokevirtual   java/io/ByteArrayOutputStream.close:()V
        //  1371: goto            1390
        //  1374: astore_2       
        //  1375: getstatic       com/baidu/location/d/a.a:Ljava/lang/String;
        //  1378: astore_2       
        //  1379: ldc             "close baos IOException!"
        //  1381: astore          5
        //  1383: aload_2        
        //  1384: aload           5
        //  1386: invokestatic    android/util/Log.d:(Ljava/lang/String;Ljava/lang/String;)I
        //  1389: pop            
        //  1390: aload_1        
        //  1391: athrow         
        //  1392: iload_3        
        //  1393: ifgt            1425
        //  1396: getstatic       com/baidu/location/d/e.o:I
        //  1399: iload           6
        //  1401: iadd           
        //  1402: istore_3       
        //  1403: iload_3        
        //  1404: putstatic       com/baidu/location/d/e.o:I
        //  1407: aload_0        
        //  1408: getfield        com/baidu/location/d/g.c:Lcom/baidu/location/d/e;
        //  1411: astore_1       
        //  1412: aload_1        
        //  1413: aconst_null    
        //  1414: putfield        com/baidu/location/d/e.j:Ljava/lang/String;
        //  1417: aload_1        
        //  1418: iconst_0       
        //  1419: invokevirtual   com/baidu/location/d/e.a:(Z)V
        //  1422: goto            1429
        //  1425: iconst_0       
        //  1426: putstatic       com/baidu/location/d/e.o:I
        //  1429: return         
        //    Exceptions:
        //  Try           Handler
        //  Start  End    Start  End    Type                 
        //  -----  -----  -----  -----  ---------------------
        //  53     56     1126   1143   Ljava/lang/Exception;
        //  53     56     1000   1017   Ljava/lang/Error;
        //  53     56     980    993    Any
        //  58     62     1126   1143   Ljava/lang/Exception;
        //  58     62     1000   1017   Ljava/lang/Error;
        //  58     62     980    993    Any
        //  64     69     1126   1143   Ljava/lang/Exception;
        //  64     69     1000   1017   Ljava/lang/Error;
        //  64     69     980    993    Any
        //  73     78     1126   1143   Ljava/lang/Exception;
        //  73     78     1000   1017   Ljava/lang/Error;
        //  73     78     980    993    Any
        //  78     81     1126   1143   Ljava/lang/Exception;
        //  78     81     1000   1017   Ljava/lang/Error;
        //  78     81     980    993    Any
        //  83     88     1126   1143   Ljava/lang/Exception;
        //  83     88     1000   1017   Ljava/lang/Error;
        //  83     88     980    993    Any
        //  88     92     1126   1143   Ljava/lang/Exception;
        //  88     92     1000   1017   Ljava/lang/Error;
        //  88     92     980    993    Any
        //  94     99     1126   1143   Ljava/lang/Exception;
        //  94     99     1000   1017   Ljava/lang/Error;
        //  94     99     980    993    Any
        //  101    108    1126   1143   Ljava/lang/Exception;
        //  101    108    1000   1017   Ljava/lang/Error;
        //  101    108    980    993    Any
        //  110    117    1126   1143   Ljava/lang/Exception;
        //  110    117    1000   1017   Ljava/lang/Error;
        //  110    117    980    993    Any
        //  119    126    1126   1143   Ljava/lang/Exception;
        //  119    126    1000   1017   Ljava/lang/Error;
        //  119    126    980    993    Any
        //  133    140    1126   1143   Ljava/lang/Exception;
        //  133    140    1000   1017   Ljava/lang/Error;
        //  133    140    980    993    Any
        //  142    147    1126   1143   Ljava/lang/Exception;
        //  142    147    1000   1017   Ljava/lang/Error;
        //  142    147    980    993    Any
        //  149    156    1126   1143   Ljava/lang/Exception;
        //  149    156    1000   1017   Ljava/lang/Error;
        //  149    156    980    993    Any
        //  158    163    1126   1143   Ljava/lang/Exception;
        //  158    163    1000   1017   Ljava/lang/Error;
        //  158    163    980    993    Any
        //  167    173    1126   1143   Ljava/lang/Exception;
        //  167    173    1000   1017   Ljava/lang/Error;
        //  167    173    980    993    Any
        //  179    185    1126   1143   Ljava/lang/Exception;
        //  179    185    1000   1017   Ljava/lang/Error;
        //  179    185    980    993    Any
        //  185    192    1126   1143   Ljava/lang/Exception;
        //  185    192    1000   1017   Ljava/lang/Error;
        //  185    192    980    993    Any
        //  196    202    1126   1143   Ljava/lang/Exception;
        //  196    202    1000   1017   Ljava/lang/Error;
        //  196    202    980    993    Any
        //  208    214    1126   1143   Ljava/lang/Exception;
        //  208    214    1000   1017   Ljava/lang/Error;
        //  208    214    980    993    Any
        //  217    222    1126   1143   Ljava/lang/Exception;
        //  217    222    1000   1017   Ljava/lang/Error;
        //  217    222    980    993    Any
        //  229    234    1126   1143   Ljava/lang/Exception;
        //  229    234    1000   1017   Ljava/lang/Error;
        //  229    234    980    993    Any
        //  241    247    1126   1143   Ljava/lang/Exception;
        //  241    247    1000   1017   Ljava/lang/Error;
        //  241    247    980    993    Any
        //  247    252    1126   1143   Ljava/lang/Exception;
        //  247    252    1000   1017   Ljava/lang/Error;
        //  247    252    980    993    Any
        //  254    259    1126   1143   Ljava/lang/Exception;
        //  254    259    1000   1017   Ljava/lang/Error;
        //  254    259    980    993    Any
        //  267    272    956    980    Ljava/lang/Exception;
        //  267    272    932    956    Ljava/lang/Error;
        //  267    272    916    932    Any
        //  274    279    956    980    Ljava/lang/Exception;
        //  274    279    932    956    Ljava/lang/Error;
        //  274    279    916    932    Any
        //  281    286    956    980    Ljava/lang/Exception;
        //  281    286    932    956    Ljava/lang/Error;
        //  281    286    916    932    Any
        //  288    292    956    980    Ljava/lang/Exception;
        //  288    292    932    956    Ljava/lang/Error;
        //  288    292    916    932    Any
        //  292    295    956    980    Ljava/lang/Exception;
        //  292    295    932    956    Ljava/lang/Error;
        //  292    295    916    932    Any
        //  299    304    956    980    Ljava/lang/Exception;
        //  299    304    932    956    Ljava/lang/Error;
        //  299    304    916    932    Any
        //  304    307    956    980    Ljava/lang/Exception;
        //  304    307    932    956    Ljava/lang/Error;
        //  304    307    916    932    Any
        //  311    316    956    980    Ljava/lang/Exception;
        //  311    316    932    956    Ljava/lang/Error;
        //  311    316    916    932    Any
        //  328    333    956    980    Ljava/lang/Exception;
        //  328    333    932    956    Ljava/lang/Error;
        //  328    333    916    932    Any
        //  345    350    956    980    Ljava/lang/Exception;
        //  345    350    932    956    Ljava/lang/Error;
        //  345    350    916    932    Any
        //  362    367    956    980    Ljava/lang/Exception;
        //  362    367    932    956    Ljava/lang/Error;
        //  362    367    916    932    Any
        //  367    371    956    980    Ljava/lang/Exception;
        //  367    371    932    956    Ljava/lang/Error;
        //  367    371    916    932    Any
        //  373    378    956    980    Ljava/lang/Exception;
        //  373    378    932    956    Ljava/lang/Error;
        //  373    378    916    932    Any
        //  389    393    956    980    Ljava/lang/Exception;
        //  389    393    932    956    Ljava/lang/Error;
        //  389    393    916    932    Any
        //  399    404    956    980    Ljava/lang/Exception;
        //  399    404    932    956    Ljava/lang/Error;
        //  399    404    916    932    Any
        //  404    409    956    980    Ljava/lang/Exception;
        //  404    409    932    956    Ljava/lang/Error;
        //  404    409    916    932    Any
        //  411    416    887    901    Ljava/lang/Exception;
        //  411    416    858    872    Ljava/lang/Error;
        //  411    416    839    852    Any
        //  418    423    887    901    Ljava/lang/Exception;
        //  418    423    858    872    Ljava/lang/Error;
        //  418    423    839    852    Any
        //  427    432    887    901    Ljava/lang/Exception;
        //  427    432    858    872    Ljava/lang/Error;
        //  427    432    839    852    Any
        //  432    437    887    901    Ljava/lang/Exception;
        //  432    437    858    872    Ljava/lang/Error;
        //  432    437    839    852    Any
        //  437    442    887    901    Ljava/lang/Exception;
        //  437    442    858    872    Ljava/lang/Error;
        //  437    442    839    852    Any
        //  456    461    887    901    Ljava/lang/Exception;
        //  456    461    858    872    Ljava/lang/Error;
        //  456    461    839    852    Any
        //  463    468    697    708    Ljava/lang/Exception;
        //  463    468    686    697    Ljava/lang/Error;
        //  463    468    676    686    Any
        //  481    486    697    708    Ljava/lang/Exception;
        //  481    486    686    697    Ljava/lang/Error;
        //  481    486    676    686    Any
        //  493    496    697    708    Ljava/lang/Exception;
        //  493    496    686    697    Ljava/lang/Error;
        //  493    496    676    686    Any
        //  498    501    697    708    Ljava/lang/Exception;
        //  498    501    686    697    Ljava/lang/Error;
        //  498    501    676    686    Any
        //  505    510    697    708    Ljava/lang/Exception;
        //  505    510    686    697    Ljava/lang/Error;
        //  505    510    676    686    Any
        //  512    517    697    708    Ljava/lang/Exception;
        //  512    517    686    697    Ljava/lang/Error;
        //  512    517    676    686    Any
        //  521    524    697    708    Ljava/lang/Exception;
        //  521    524    686    697    Ljava/lang/Error;
        //  521    524    676    686    Any
        //  526    531    697    708    Ljava/lang/Exception;
        //  526    531    686    697    Ljava/lang/Error;
        //  526    531    676    686    Any
        //  536    540    671    676    Ljava/lang/Exception;
        //  536    540    666    671    Ljava/lang/Error;
        //  536    540    662    666    Any
        //  544    549    671    676    Ljava/lang/Exception;
        //  544    549    666    671    Ljava/lang/Error;
        //  544    549    662    666    Any
        //  566    571    671    676    Ljava/lang/Exception;
        //  566    571    666    671    Ljava/lang/Error;
        //  566    571    662    666    Any
        //  574    578    671    676    Ljava/lang/Exception;
        //  574    578    666    671    Ljava/lang/Error;
        //  574    578    662    666    Any
        //  580    583    671    676    Ljava/lang/Exception;
        //  580    583    666    671    Ljava/lang/Error;
        //  580    583    662    666    Any
        //  585    590    671    676    Ljava/lang/Exception;
        //  585    590    666    671    Ljava/lang/Error;
        //  585    590    662    666    Any
        //  600    605    671    676    Ljava/lang/Exception;
        //  600    605    666    671    Ljava/lang/Error;
        //  600    605    662    666    Any
        //  607    612    671    676    Ljava/lang/Exception;
        //  607    612    666    671    Ljava/lang/Error;
        //  607    612    662    666    Any
        //  612    616    671    676    Ljava/lang/Exception;
        //  612    616    666    671    Ljava/lang/Error;
        //  612    616    662    666    Any
        //  623    627    671    676    Ljava/lang/Exception;
        //  623    627    666    671    Ljava/lang/Error;
        //  623    627    662    666    Any
        //  629    634    671    676    Ljava/lang/Exception;
        //  629    634    666    671    Ljava/lang/Error;
        //  629    634    662    666    Any
        //  638    643    671    676    Ljava/lang/Exception;
        //  638    643    666    671    Ljava/lang/Error;
        //  638    643    662    666    Any
        //  643    647    671    676    Ljava/lang/Exception;
        //  643    647    666    671    Ljava/lang/Error;
        //  643    647    662    666    Any
        //  651    656    671    676    Ljava/lang/Exception;
        //  651    656    666    671    Ljava/lang/Error;
        //  651    656    662    666    Any
        //  741    746    749    768    Ljava/lang/Exception;
        //  773    778    781    800    Ljava/lang/Exception;
        //  805    810    813    832    Ljava/lang/Exception;
        //  1017   1020   1288   1295   Any
        //  1028   1034   1288   1295   Any
        //  1049   1054   1057   1076   Ljava/lang/Exception;
        //  1081   1086   1089   1108   Ljava/lang/Exception;
        //  1113   1118   1121   1126   Ljava/lang/Exception;
        //  1143   1146   1288   1295   Any
        //  1155   1161   1288   1295   Any
        //  1176   1181   1184   1203   Ljava/lang/Exception;
        //  1208   1213   1216   1235   Ljava/lang/Exception;
        //  1240   1245   1248   1250   Ljava/lang/Exception;
        //  1309   1313   1316   1332   Ljava/lang/Exception;
        //  1337   1342   1345   1361   Ljava/lang/Exception;
        //  1366   1371   1374   1390   Ljava/lang/Exception;
        // 
        // The error that occurred was:
        // 
        // java.lang.IndexOutOfBoundsException: Index: 684, Size: 684
        //     at java.util.ArrayList.rangeCheck(ArrayList.java:657)
        //     at java.util.ArrayList.get(ArrayList.java:433)
        //     at com.strobel.decompiler.ast.AstBuilder.convertToAst(AstBuilder.java:3303)
        //     at com.strobel.decompiler.ast.AstBuilder.convertToAst(AstBuilder.java:3551)
        //     at com.strobel.decompiler.ast.AstBuilder.build(AstBuilder.java:113)
        //     at com.strobel.decompiler.languages.java.ast.AstMethodBodyBuilder.createMethodBody(AstMethodBodyBuilder.java:210)
        //     at com.strobel.decompiler.languages.java.ast.AstMethodBodyBuilder.createMethodBody(AstMethodBodyBuilder.java:99)
        //     at com.strobel.decompiler.languages.java.ast.AstBuilder.createMethodBody(AstBuilder.java:757)
        //     at com.strobel.decompiler.languages.java.ast.AstBuilder.createMethod(AstBuilder.java:655)
        //     at com.strobel.decompiler.languages.java.ast.AstBuilder.addTypeMembers(AstBuilder.java:532)
        //     at com.strobel.decompiler.languages.java.ast.AstBuilder.createTypeCore(AstBuilder.java:499)
        //     at com.strobel.decompiler.languages.java.ast.AstBuilder.createTypeNoCache(AstBuilder.java:141)
        //     at com.strobel.decompiler.languages.java.ast.AstBuilder.createType(AstBuilder.java:130)
        //     at com.strobel.decompiler.languages.java.ast.AstBuilder.addType(AstBuilder.java:105)
        //     at com.strobel.decompiler.languages.java.JavaLanguage.buildAst(JavaLanguage.java:71)
        //     at com.strobel.decompiler.languages.java.JavaLanguage.decompileType(JavaLanguage.java:59)
        //     at com.strobel.decompiler.DecompilerDriver.decompileType(DecompilerDriver.java:317)
        //     at com.strobel.decompiler.DecompilerDriver.decompileJar(DecompilerDriver.java:238)
        //     at com.strobel.decompiler.DecompilerDriver.main(DecompilerDriver.java:138)
        // 
        throw new IllegalStateException("An error occurred while decompiling this method.");
    }
}
